aksdp/data/__init__.py
aksdp/data/data.py
aksdp/data/dataframe_data.py
aksdp/data/json_data.py
aksdp/data/raw_data.py
aksdp/data/sqlalchemy_model_data.py
aksdp/dataset/__init__.py
aksdp/dataset/dataset.py
aksdp/graph/__init__.py
aksdp/graph/concurrent_graph.py
aksdp/graph/debug_graph.py
aksdp/graph/graph.py
aksdp/graph/graph_task.py
aksdp/repository/__init__.py
aksdp/repository/localfile_repository.py
aksdp/repository/pandas_db_repository.py
aksdp/repository/repository.py
aksdp/repository/s3file_repository.py
aksdp/repository/sqlalchemy_repository.py
aksdp/task/__init__.py
aksdp/task/task.py
aksdp/util/__init__.py
aksdp/util/airflow.py
aksdp/util/graph_factory.py
aksdp/util/plantuml.py
aksdp-0.0.1.post6.dist-info/LICENSE
aksdp-0.0.1.post6.dist-info/WHEEL
aksdp-0.0.1.post6.dist-info/METADATA
aksdp-0.0.1.post6.dist-info/RECORD
